package_creation_tutorial/__init__.py
package_creation_tutorial/main.py
package_creation_tutorial/string_ops.py
package_chiheb_creation_tutorial-0.1.0.dist-info/METADATA
package_chiheb_creation_tutorial-0.1.0.dist-info/WHEEL
package_chiheb_creation_tutorial-0.1.0.dist-info/RECORD
